<?xml version="1.0" encoding="UTF-8" standalone="no"?>
<Gesture AppName="Gestures" AppVer="3.5.0.0" Date="Monday, March 05, 2007" Millseconds="1268" Name="circle01" NumPts="344" Number="1" Speed="medium" Subject="2" TimeOfDay="9:12:24 PM">
    <Point T="0" X="362.0" Y="82.0"/>
    <Point T="0" X="362.0" Y="82.0"/>
    <Point T="0" X="361.0" Y="82.0"/>
    <Point T="0" X="361.0" Y="82.0"/>
    <Point T="0" X="361.0" Y="82.0"/>
    <Point T="0" X="361.0" Y="83.0"/>
    <Point T="0" X="360.0" Y="83.0"/>
    <Point T="0" X="360.0" Y="83.0"/>
    <Point T="0" X="360.0" Y="83.0"/>
    <Point T="0" X="359.0" Y="84.0"/>
    <Point T="0" X="359.0" Y="84.0"/>
    <Point T="0" X="359.0" Y="85.0"/>
    <Point T="0" X="358.0" Y="85.0"/>
    <Point T="0" X="358.0" Y="85.0"/>
    <Point T="0" X="358.0" Y="86.0"/>
    <Point T="0" X="358.0" Y="86.0"/>
    <Point T="0" X="357.0" Y="86.0"/>
    <Point T="0" X="357.0" Y="86.0"/>
    <Point T="0" X="357.0" Y="87.0"/>
    <Point T="0" X="357.0" Y="87.0"/>
    <Point T="0" X="357.0" Y="87.0"/>
    <Point T="0" X="357.0" Y="87.0"/>
    <Point T="0" X="356.0" Y="88.0"/>
    <Point T="0" X="356.0" Y="88.0"/>
    <Point T="0" X="356.0" Y="88.0"/>
    <Point T="0" X="356.0" Y="88.0"/>
    <Point T="0" X="356.0" Y="89.0"/>
    <Point T="0" X="356.0" Y="89.0"/>
    <Point T="0" X="355.0" Y="89.0"/>
    <Point T="0" X="355.0" Y="90.0"/>
    <Point T="0" X="355.0" Y="90.0"/>
    <Point T="0" X="355.0" Y="90.0"/>
    <Point T="0" X="355.0" Y="91.0"/>
    <Point T="0" X="355.0" Y="91.0"/>
    <Point T="0" X="355.0" Y="91.0"/>
    <Point T="0" X="355.0" Y="92.0"/>
    <Point T="0" X="354.0" Y="92.0"/>
    <Point T="0" X="354.0" Y="92.0"/>
    <Point T="0" X="354.0" Y="93.0"/>
    <Point T="0" X="354.0" Y="93.0"/>
    <Point T="0" X="354.0" Y="93.0"/>
    <Point T="0" X="354.0" Y="94.0"/>
    <Point T="0" X="354.0" Y="94.0"/>
    <Point T="0" X="354.0" Y="95.0"/>
    <Point T="0" X="354.0" Y="95.0"/>
    <Point T="0" X="354.0" Y="96.0"/>
    <Point T="0" X="354.0" Y="96.0"/>
    <Point T="0" X="354.0" Y="97.0"/>
    <Point T="0" X="354.0" Y="97.0"/>
    <Point T="0" X="353.0" Y="98.0"/>
    <Point T="0" X="353.0" Y="98.0"/>
    <Point T="0" X="353.0" Y="99.0"/>
    <Point T="0" X="353.0" Y="99.0"/>
    <Point T="0" X="353.0" Y="100.0"/>
    <Point T="0" X="353.0" Y="100.0"/>
    <Point T="0" X="353.0" Y="101.0"/>
    <Point T="0" X="353.0" Y="101.0"/>
    <Point T="0" X="353.0" Y="101.0"/>
    <Point T="0" X="353.0" Y="102.0"/>
    <Point T="0" X="353.0" Y="102.0"/>
    <Point T="0" X="353.0" Y="103.0"/>
    <Point T="0" X="353.0" Y="104.0"/>
    <Point T="0" X="353.0" Y="104.0"/>
    <Point T="0" X="353.0" Y="105.0"/>
    <Point T="0" X="353.0" Y="105.0"/>
    <Point T="0" X="354.0" Y="106.0"/>
    <Point T="0" X="354.0" Y="106.0"/>
    <Point T="0" X="354.0" Y="107.0"/>
    <Point T="0" X="354.0" Y="107.0"/>
    <Point T="0" X="354.0" Y="108.0"/>
    <Point T="0" X="354.0" Y="108.0"/>
    <Point T="0" X="355.0" Y="108.0"/>
    <Point T="0" X="355.0" Y="109.0"/>
    <Point T="0" X="355.0" Y="109.0"/>
    <Point T="0" X="355.0" Y="110.0"/>
    <Point T="0" X="356.0" Y="110.0"/>
    <Point T="0" X="356.0" Y="111.0"/>
    <Point T="0" X="356.0" Y="111.0"/>
    <Point T="0" X="357.0" Y="112.0"/>
    <Point T="0" X="357.0" Y="112.0"/>
    <Point T="0" X="358.0" Y="113.0"/>
    <Point T="0" X="358.0" Y="113.0"/>
    <Point T="0" X="358.0" Y="113.0"/>
    <Point T="0" X="358.0" Y="114.0"/>
    <Point T="0" X="359.0" Y="114.0"/>
    <Point T="0" X="359.0" Y="115.0"/>
    <Point T="0" X="360.0" Y="115.0"/>
    <Point T="0" X="361.0" Y="115.0"/>
    <Point T="0" X="361.0" Y="116.0"/>
    <Point T="0" X="362.0" Y="116.0"/>
    <Point T="0" X="362.0" Y="117.0"/>
    <Point T="0" X="362.0" Y="117.0"/>
    <Point T="0" X="363.0" Y="117.0"/>
    <Point T="0" X="363.0" Y="117.0"/>
    <Point T="0" X="363.0" Y="117.0"/>
    <Point T="0" X="363.0" Y="118.0"/>
    <Point T="0" X="364.0" Y="118.0"/>
    <Point T="0" X="364.0" Y="118.0"/>
    <Point T="0" X="365.0" Y="118.0"/>
    <Point T="0" X="365.0" Y="118.0"/>
    <Point T="0" X="365.0" Y="119.0"/>
    <Point T="0" X="366.0" Y="119.0"/>
    <Point T="0" X="366.0" Y="119.0"/>
    <Point T="0" X="367.0" Y="120.0"/>
    <Point T="0" X="367.0" Y="120.0"/>
    <Point T="0" X="368.0" Y="120.0"/>
    <Point T="0" X="368.0" Y="120.0"/>
    <Point T="0" X="368.0" Y="120.0"/>
    <Point T="0" X="369.0" Y="120.0"/>
    <Point T="0" X="369.0" Y="120.0"/>
    <Point T="0" X="369.0" Y="120.0"/>
    <Point T="0" X="370.0" Y="121.0"/>
    <Point T="0" X="370.0" Y="121.0"/>
    <Point T="0" X="370.0" Y="121.0"/>
    <Point T="0" X="371.0" Y="121.0"/>
    <Point T="0" X="371.0" Y="121.0"/>
    <Point T="0" X="372.0" Y="121.0"/>
    <Point T="0" X="372.0" Y="121.0"/>
    <Point T="0" X="373.0" Y="121.0"/>
    <Point T="0" X="373.0" Y="121.0"/>
    <Point T="0" X="373.0" Y="121.0"/>
    <Point T="0" X="374.0" Y="121.0"/>
    <Point T="0" X="375.0" Y="121.0"/>
    <Point T="0" X="376.0" Y="121.0"/>
    <Point T="0" X="376.0" Y="121.0"/>
    <Point T="0" X="377.0" Y="121.0"/>
    <Point T="0" X="377.0" Y="121.0"/>
    <Point T="0" X="378.0" Y="121.0"/>
    <Point T="0" X="379.0" Y="121.0"/>
    <Point T="0" X="379.0" Y="121.0"/>
    <Point T="0" X="380.0" Y="121.0"/>
    <Point T="0" X="381.0" Y="121.0"/>
    <Point T="0" X="381.0" Y="121.0"/>
    <Point T="0" X="382.0" Y="121.0"/>
    <Point T="0" X="382.0" Y="121.0"/>
    <Point T="0" X="383.0" Y="120.0"/>
    <Point T="0" X="383.0" Y="120.0"/>
    <Point T="0" X="384.0" Y="120.0"/>
    <Point T="0" X="384.0" Y="120.0"/>
    <Point T="0" X="385.0" Y="120.0"/>
    <Point T="0" X="385.0" Y="120.0"/>
    <Point T="0" X="385.0" Y="119.0"/>
    <Point T="0" X="385.0" Y="119.0"/>
    <Point T="0" X="386.0" Y="119.0"/>
    <Point T="0" X="387.0" Y="119.0"/>
    <Point T="0" X="387.0" Y="118.0"/>
    <Point T="0" X="387.0" Y="118.0"/>
    <Point T="0" X="388.0" Y="118.0"/>
    <Point T="0" X="388.0" Y="117.0"/>
    <Point T="0" X="389.0" Y="117.0"/>
    <Point T="0" X="389.0" Y="117.0"/>
    <Point T="0" X="389.0" Y="117.0"/>
    <Point T="0" X="390.0" Y="116.0"/>
    <Point T="0" X="390.0" Y="116.0"/>
    <Point T="0" X="390.0" Y="116.0"/>
    <Point T="0" X="391.0" Y="116.0"/>
    <Point T="0" X="391.0" Y="115.0"/>
    <Point T="0" X="391.0" Y="115.0"/>
    <Point T="0" X="392.0" Y="114.0"/>
    <Point T="0" X="392.0" Y="114.0"/>
    <Point T="0" X="392.0" Y="114.0"/>
    <Point T="0" X="392.0" Y="114.0"/>
    <Point T="0" X="392.0" Y="113.0"/>
    <Point T="0" X="393.0" Y="113.0"/>
    <Point T="0" X="393.0" Y="113.0"/>
    <Point T="0" X="393.0" Y="112.0"/>
    <Point T="0" X="393.0" Y="112.0"/>
    <Point T="0" X="393.0" Y="112.0"/>
    <Point T="0" X="394.0" Y="111.0"/>
    <Point T="0" X="394.0" Y="111.0"/>
    <Point T="0" X="394.0" Y="111.0"/>
    <Point T="0" X="394.0" Y="110.0"/>
    <Point T="0" X="394.0" Y="110.0"/>
    <Point T="0" X="394.0" Y="110.0"/>
    <Point T="0" X="394.0" Y="109.0"/>
    <Point T="0" X="394.0" Y="109.0"/>
    <Point T="0" X="394.0" Y="109.0"/>
    <Point T="0" X="394.0" Y="109.0"/>
    <Point T="0" X="394.0" Y="108.0"/>
    <Point T="0" X="394.0" Y="108.0"/>
    <Point T="0" X="394.0" Y="108.0"/>
    <Point T="0" X="394.0" Y="107.0"/>
    <Point T="0" X="394.0" Y="107.0"/>
    <Point T="0" X="394.0" Y="107.0"/>
    <Point T="0" X="394.0" Y="107.0"/>
    <Point T="0" X="394.0" Y="106.0"/>
    <Point T="0" X="394.0" Y="106.0"/>
    <Point T="0" X="394.0" Y="106.0"/>
    <Point T="0" X="394.0" Y="106.0"/>
    <Point T="0" X="394.0" Y="105.0"/>
    <Point T="0" X="394.0" Y="105.0"/>
    <Point T="0" X="394.0" Y="103.0"/>
    <Point T="0" X="394.0" Y="102.0"/>
    <Point T="0" X="394.0" Y="102.0"/>
    <Point T="0" X="394.0" Y="101.0"/>
    <Point T="0" X="394.0" Y="100.0"/>
    <Point T="0" X="394.0" Y="100.0"/>
    <Point T="0" X="394.0" Y="100.0"/>
    <Point T="0" X="393.0" Y="99.0"/>
    <Point T="0" X="393.0" Y="99.0"/>
    <Point T="0" X="393.0" Y="98.0"/>
    <Point T="0" X="392.0" Y="97.0"/>
    <Point T="0" X="392.0" Y="97.0"/>
    <Point T="0" X="392.0" Y="96.0"/>
    <Point T="0" X="392.0" Y="96.0"/>
    <Point T="0" X="392.0" Y="96.0"/>
    <Point T="0" X="392.0" Y="96.0"/>
    <Point T="0" X="392.0" Y="95.0"/>
    <Point T="0" X="392.0" Y="95.0"/>
    <Point T="0" X="391.0" Y="95.0"/>
    <Point T="0" X="391.0" Y="94.0"/>
    <Point T="0" X="391.0" Y="94.0"/>
    <Point T="0" X="391.0" Y="94.0"/>
    <Point T="0" X="391.0" Y="94.0"/>
    <Point T="0" X="391.0" Y="94.0"/>
    <Point T="0" X="391.0" Y="93.0"/>
    <Point T="0" X="390.0" Y="93.0"/>
    <Point T="0" X="390.0" Y="93.0"/>
    <Point T="0" X="390.0" Y="93.0"/>
    <Point T="0" X="390.0" Y="92.0"/>
    <Point T="0" X="389.0" Y="92.0"/>
    <Point T="0" X="389.0" Y="92.0"/>
    <Point T="0" X="389.0" Y="91.0"/>
    <Point T="0" X="389.0" Y="91.0"/>
    <Point T="0" X="388.0" Y="91.0"/>
    <Point T="0" X="388.0" Y="91.0"/>
    <Point T="0" X="388.0" Y="90.0"/>
    <Point T="0" X="388.0" Y="90.0"/>
    <Point T="0" X="387.0" Y="90.0"/>
    <Point T="0" X="387.0" Y="90.0"/>
    <Point T="0" X="387.0" Y="90.0"/>
    <Point T="0" X="386.0" Y="89.0"/>
    <Point T="0" X="386.0" Y="89.0"/>
    <Point T="0" X="386.0" Y="89.0"/>
    <Point T="0" X="386.0" Y="89.0"/>
    <Point T="0" X="385.0" Y="88.0"/>
    <Point T="0" X="385.0" Y="88.0"/>
    <Point T="0" X="385.0" Y="88.0"/>
    <Point T="0" X="384.0" Y="88.0"/>
    <Point T="0" X="384.0" Y="87.0"/>
    <Point T="0" X="384.0" Y="87.0"/>
    <Point T="0" X="383.0" Y="87.0"/>
    <Point T="0" X="383.0" Y="87.0"/>
    <Point T="0" X="383.0" Y="87.0"/>
    <Point T="0" X="383.0" Y="86.0"/>
    <Point T="0" X="382.0" Y="86.0"/>
    <Point T="0" X="382.0" Y="86.0"/>
    <Point T="0" X="382.0" Y="86.0"/>
    <Point T="0" X="381.0" Y="86.0"/>
    <Point T="0" X="381.0" Y="85.0"/>
    <Point T="0" X="381.0" Y="85.0"/>
    <Point T="0" X="381.0" Y="85.0"/>
    <Point T="0" X="381.0" Y="85.0"/>
    <Point T="0" X="380.0" Y="85.0"/>
    <Point T="0" X="380.0" Y="85.0"/>
    <Point T="0" X="380.0" Y="85.0"/>
    <Point T="0" X="380.0" Y="85.0"/>
    <Point T="0" X="380.0" Y="85.0"/>
    <Point T="0" X="379.0" Y="85.0"/>
    <Point T="0" X="379.0" Y="85.0"/>
    <Point T="0" X="379.0" Y="85.0"/>
    <Point T="0" X="379.0" Y="85.0"/>
    <Point T="0" X="378.0" Y="85.0"/>
    <Point T="0" X="378.0" Y="85.0"/>
    <Point T="0" X="378.0" Y="84.0"/>
    <Point T="0" X="378.0" Y="84.0"/>
    <Point T="0" X="377.0" Y="84.0"/>
    <Point T="0" X="377.0" Y="84.0"/>
    <Point T="0" X="377.0" Y="84.0"/>
    <Point T="0" X="377.0" Y="84.0"/>
    <Point T="0" X="377.0" Y="84.0"/>
    <Point T="0" X="376.0" Y="84.0"/>
    <Point T="0" X="376.0" Y="84.0"/>
    <Point T="0" X="376.0" Y="84.0"/>
    <Point T="0" X="376.0" Y="84.0"/>
    <Point T="0" X="375.0" Y="84.0"/>
    <Point T="0" X="375.0" Y="84.0"/>
    <Point T="0" X="375.0" Y="84.0"/>
    <Point T="0" X="375.0" Y="84.0"/>
    <Point T="0" X="374.0" Y="84.0"/>
    <Point T="0" X="374.0" Y="84.0"/>
    <Point T="0" X="374.0" Y="84.0"/>
    <Point T="0" X="374.0" Y="84.0"/>
    <Point T="0" X="373.0" Y="84.0"/>
    <Point T="0" X="373.0" Y="84.0"/>
    <Point T="0" X="373.0" Y="84.0"/>
    <Point T="0" X="372.0" Y="84.0"/>
    <Point T="0" X="372.0" Y="84.0"/>
    <Point T="0" X="372.0" Y="84.0"/>
    <Point T="0" X="371.0" Y="84.0"/>
    <Point T="0" X="371.0" Y="84.0"/>
    <Point T="0" X="371.0" Y="84.0"/>
    <Point T="0" X="371.0" Y="84.0"/>
    <Point T="0" X="370.0" Y="83.0"/>
    <Point T="0" X="370.0" Y="83.0"/>
    <Point T="0" X="369.0" Y="83.0"/>
    <Point T="0" X="369.0" Y="83.0"/>
    <Point T="0" X="369.0" Y="83.0"/>
    <Point T="0" X="369.0" Y="83.0"/>
    <Point T="0" X="368.0" Y="83.0"/>
    <Point T="0" X="368.0" Y="83.0"/>
    <Point T="0" X="368.0" Y="83.0"/>
    <Point T="0" X="367.0" Y="83.0"/>
    <Point T="0" X="367.0" Y="83.0"/>
    <Point T="0" X="367.0" Y="83.0"/>
    <Point T="0" X="367.0" Y="83.0"/>
    <Point T="0" X="366.0" Y="83.0"/>
    <Point T="0" X="366.0" Y="83.0"/>
    <Point T="0" X="366.0" Y="83.0"/>
    <Point T="0" X="365.0" Y="83.0"/>
    <Point T="0" X="365.0" Y="83.0"/>
    <Point T="0" X="365.0" Y="83.0"/>
    <Point T="0" X="365.0" Y="83.0"/>
    <Point T="0" X="364.0" Y="83.0"/>
    <Point T="0" X="364.0" Y="83.0"/>
    <Point T="0" X="364.0" Y="83.0"/>
    <Point T="0" X="364.0" Y="83.0"/>
    <Point T="0" X="363.0" Y="83.0"/>
    <Point T="0" X="363.0" Y="83.0"/>
    <Point T="0" X="363.0" Y="83.0"/>
    <Point T="0" X="363.0" Y="83.0"/>
    <Point T="0" X="362.0" Y="83.0"/>
    <Point T="0" X="362.0" Y="83.0"/>
    <Point T="0" X="362.0" Y="83.0"/>
    <Point T="0" X="362.0" Y="83.0"/>
    <Point T="0" X="362.0" Y="83.0"/>
    <Point T="0" X="361.0" Y="83.0"/>
    <Point T="0" X="361.0" Y="83.0"/>
    <Point T="0" X="361.0" Y="83.0"/>
    <Point T="0" X="361.0" Y="83.0"/>
    <Point T="0" X="360.0" Y="83.0"/>
    <Point T="0" X="360.0" Y="83.0"/>
    <Point T="0" X="360.0" Y="83.0"/>
    <Point T="0" X="359.0" Y="83.0"/>
    <Point T="0" X="359.0" Y="83.0"/>
    <Point T="0" X="358.0" Y="83.0"/>
    <Point T="0" X="358.0" Y="83.0"/>
    <Point T="0" X="358.0" Y="83.0"/>
    <Point T="0" X="357.0" Y="83.0"/>
    <Point T="0" X="357.0" Y="83.0"/>
    <Point T="0" X="357.0" Y="83.0"/>
    <Point T="0" X="357.0" Y="83.0"/>
    <Point T="0" X="356.0" Y="83.0"/>
    <Point T="0" X="356.0" Y="83.0"/>
</Gesture>
