<?xml version="1.0" encoding="UTF-8" standalone="no"?>
<Gesture AppName="Gestures" AppVer="3.5.0.0" Date="Monday, March 05, 2007" Millseconds="1268" Name="delete06" NumPts="59" Number="6" Speed="medium" Subject="2" TimeOfDay="9:12:24 PM">
<Point T="0" X="437.0" Y="86.0"/>
<Point T="0" X="437.0" Y="86.0"/>
<Point T="0" X="440.0" Y="86.0"/>
<Point T="0" X="448.0" Y="89.0"/>
<Point T="0" X="457.0" Y="93.0"/>
<Point T="0" X="464.0" Y="98.0"/>
<Point T="0" X="475.0" Y="104.0"/>
<Point T="0" X="483.0" Y="110.0"/>
<Point T="0" X="487.0" Y="114.0"/>
<Point T="0" X="489.0" Y="115.0"/>
<Point T="0" X="489.0" Y="116.0"/>
<Point T="0" X="489.0" Y="117.0"/>
<Point T="0" X="489.0" Y="117.0"/>
<Point T="0" X="489.0" Y="117.0"/>
<Point T="0" X="489.0" Y="117.0"/>
<Point T="0" X="489.0" Y="117.0"/>
<Point T="0" X="489.0" Y="117.0"/>
<Point T="0" X="488.0" Y="117.0"/>
<Point T="0" X="487.0" Y="117.0"/>
<Point T="0" X="486.0" Y="117.0"/>
<Point T="0" X="484.0" Y="117.0"/>
<Point T="0" X="481.0" Y="117.0"/>
<Point T="0" X="478.0" Y="118.0"/>
<Point T="0" X="476.0" Y="119.0"/>
<Point T="0" X="471.0" Y="120.0"/>
<Point T="0" X="467.0" Y="122.0"/>
<Point T="0" X="464.0" Y="123.0"/>
<Point T="0" X="462.0" Y="123.0"/>
<Point T="0" X="460.0" Y="124.0"/>
<Point T="0" X="460.0" Y="124.0"/>
<Point T="0" X="459.0" Y="124.0"/>
<Point T="0" X="459.0" Y="124.0"/>
<Point T="0" X="459.0" Y="124.0"/>
<Point T="0" X="457.0" Y="124.0"/>
<Point T="0" X="454.0" Y="125.0"/>
<Point T="0" X="451.0" Y="126.0"/>
<Point T="0" X="450.0" Y="127.0"/>
<Point T="0" X="448.0" Y="128.0"/>
<Point T="0" X="448.0" Y="128.0"/>
<Point T="0" X="448.0" Y="128.0"/>
<Point T="0" X="448.0" Y="128.0"/>
<Point T="0" X="448.0" Y="127.0"/>
<Point T="0" X="448.0" Y="126.0"/>
<Point T="0" X="448.0" Y="124.0"/>
<Point T="0" X="449.0" Y="120.0"/>
<Point T="0" X="452.0" Y="112.0"/>
<Point T="0" X="457.0" Y="103.0"/>
<Point T="0" X="461.0" Y="94.0"/>
<Point T="0" X="465.0" Y="87.0"/>
<Point T="0" X="467.0" Y="82.0"/>
<Point T="0" X="468.0" Y="80.0"/>
<Point T="0" X="469.0" Y="79.0"/>
<Point T="0" X="470.0" Y="78.0"/>
<Point T="0" X="471.0" Y="76.0"/>
<Point T="0" X="472.0" Y="75.0"/>
<Point T="0" X="473.0" Y="74.0"/>
<Point T="0" X="474.0" Y="73.0"/>
<Point T="0" X="474.0" Y="73.0"/>
<Point T="0" X="473.0" Y="73.0"/>
</Gesture>
