<?xml version="1.0" encoding="UTF-8" standalone="no"?>
<Gesture AppName="Gestures" AppVer="3.5.0.0" Date="Monday, March 05, 2007" Millseconds="1268" Name="right_square_braces02" NumPts="57" Number="2" Speed="medium" Subject="2" TimeOfDay="9:12:24 PM">
<Point T="0" X="219.0" Y="30.0"/>
<Point T="0" X="219.0" Y="30.0"/>
<Point T="0" X="219.0" Y="30.0"/>
<Point T="0" X="221.0" Y="30.0"/>
<Point T="0" X="225.0" Y="30.0"/>
<Point T="0" X="228.0" Y="30.0"/>
<Point T="0" X="230.0" Y="30.0"/>
<Point T="0" X="231.0" Y="30.0"/>
<Point T="0" X="232.0" Y="30.0"/>
<Point T="0" X="232.0" Y="30.0"/>
<Point T="0" X="232.0" Y="31.0"/>
<Point T="0" X="232.0" Y="33.0"/>
<Point T="0" X="232.0" Y="35.0"/>
<Point T="0" X="233.0" Y="37.0"/>
<Point T="0" X="233.0" Y="39.0"/>
<Point T="0" X="233.0" Y="41.0"/>
<Point T="0" X="234.0" Y="43.0"/>
<Point T="0" X="234.0" Y="45.0"/>
<Point T="0" X="234.0" Y="49.0"/>
<Point T="0" X="234.0" Y="54.0"/>
<Point T="0" X="234.0" Y="58.0"/>
<Point T="0" X="234.0" Y="62.0"/>
<Point T="0" X="234.0" Y="64.0"/>
<Point T="0" X="233.0" Y="65.0"/>
<Point T="0" X="233.0" Y="67.0"/>
<Point T="0" X="233.0" Y="71.0"/>
<Point T="0" X="232.0" Y="76.0"/>
<Point T="0" X="232.0" Y="79.0"/>
<Point T="0" X="232.0" Y="81.0"/>
<Point T="0" X="232.0" Y="82.0"/>
<Point T="0" X="232.0" Y="82.0"/>
<Point T="0" X="232.0" Y="82.0"/>
<Point T="0" X="231.0" Y="82.0"/>
<Point T="0" X="231.0" Y="82.0"/>
<Point T="0" X="231.0" Y="82.0"/>
<Point T="0" X="230.0" Y="82.0"/>
<Point T="0" X="229.0" Y="82.0"/>
<Point T="0" X="228.0" Y="82.0"/>
<Point T="0" X="227.0" Y="82.0"/>
<Point T="0" X="226.0" Y="82.0"/>
<Point T="0" X="225.0" Y="82.0"/>
<Point T="0" X="224.0" Y="82.0"/>
<Point T="0" X="222.0" Y="81.0"/>
<Point T="0" X="222.0" Y="81.0"/>
<Point T="0" X="221.0" Y="81.0"/>
<Point T="0" X="221.0" Y="81.0"/>
<Point T="0" X="220.0" Y="81.0"/>
<Point T="0" X="220.0" Y="81.0"/>
<Point T="0" X="220.0" Y="81.0"/>
<Point T="0" X="220.0" Y="81.0"/>
<Point T="0" X="220.0" Y="81.0"/>
<Point T="0" X="220.0" Y="81.0"/>
<Point T="0" X="220.0" Y="81.0"/>
<Point T="0" X="219.0" Y="81.0"/>
<Point T="0" X="219.0" Y="81.0"/>
<Point T="0" X="219.0" Y="81.0"/>
<Point T="0" X="219.0" Y="80.0"/>
</Gesture>
