<?xml version="1.0" encoding="UTF-8" standalone="no"?>
<Gesture AppName="Gestures" AppVer="3.5.0.0" Date="Monday, March 05, 2007" Millseconds="1268" Name="left_square_braces01" NumPts="49" Number="1" Speed="medium" Subject="2" TimeOfDay="9:12:24 PM">
<Point T="0" X="306.0" Y="85.0"/>
<Point T="0" X="305.0" Y="85.0"/>
<Point T="0" X="305.0" Y="85.0"/>
<Point T="0" X="303.0" Y="85.0"/>
<Point T="0" X="301.0" Y="85.0"/>
<Point T="0" X="299.0" Y="85.0"/>
<Point T="0" X="296.0" Y="85.0"/>
<Point T="0" X="293.0" Y="85.0"/>
<Point T="0" X="292.0" Y="85.0"/>
<Point T="0" X="292.0" Y="85.0"/>
<Point T="0" X="292.0" Y="86.0"/>
<Point T="0" X="293.0" Y="87.0"/>
<Point T="0" X="294.0" Y="88.0"/>
<Point T="0" X="295.0" Y="90.0"/>
<Point T="0" X="295.0" Y="93.0"/>
<Point T="0" X="296.0" Y="98.0"/>
<Point T="0" X="296.0" Y="103.0"/>
<Point T="0" X="296.0" Y="108.0"/>
<Point T="0" X="297.0" Y="112.0"/>
<Point T="0" X="297.0" Y="114.0"/>
<Point T="0" X="297.0" Y="115.0"/>
<Point T="0" X="297.0" Y="115.0"/>
<Point T="0" X="297.0" Y="116.0"/>
<Point T="0" X="297.0" Y="118.0"/>
<Point T="0" X="297.0" Y="120.0"/>
<Point T="0" X="297.0" Y="123.0"/>
<Point T="0" X="297.0" Y="125.0"/>
<Point T="0" X="297.0" Y="127.0"/>
<Point T="0" X="297.0" Y="127.0"/>
<Point T="0" X="297.0" Y="128.0"/>
<Point T="0" X="297.0" Y="128.0"/>
<Point T="0" X="297.0" Y="128.0"/>
<Point T="0" X="297.0" Y="128.0"/>
<Point T="0" X="297.0" Y="128.0"/>
<Point T="0" X="298.0" Y="128.0"/>
<Point T="0" X="298.0" Y="128.0"/>
<Point T="0" X="299.0" Y="128.0"/>
<Point T="0" X="301.0" Y="127.0"/>
<Point T="0" X="303.0" Y="127.0"/>
<Point T="0" X="306.0" Y="126.0"/>
<Point T="0" X="308.0" Y="126.0"/>
<Point T="0" X="311.0" Y="126.0"/>
<Point T="0" X="313.0" Y="125.0"/>
<Point T="0" X="315.0" Y="125.0"/>
<Point T="0" X="316.0" Y="125.0"/>
<Point T="0" X="317.0" Y="125.0"/>
<Point T="0" X="318.0" Y="125.0"/>
<Point T="0" X="318.0" Y="125.0"/>
<Point T="0" X="318.0" Y="125.0"/>
</Gesture>
