<?xml version="1.0" encoding="UTF-8" standalone="no"?>
<Gesture AppName="Gestures" AppVer="3.5.0.0" Date="Monday, March 05, 2007" Millseconds="1268" Name="triangle06" NumPts="67" Number="6" Speed="medium" Subject="2" TimeOfDay="9:12:24 PM">
<Point T="0" X="258.0" Y="75.0"/>
<Point T="0" X="258.0" Y="75.0"/>
<Point T="0" X="257.0" Y="77.0"/>
<Point T="0" X="255.0" Y="84.0"/>
<Point T="0" X="251.0" Y="92.0"/>
<Point T="0" X="247.0" Y="102.0"/>
<Point T="0" X="243.0" Y="113.0"/>
<Point T="0" X="240.0" Y="121.0"/>
<Point T="0" X="239.0" Y="126.0"/>
<Point T="0" X="239.0" Y="128.0"/>
<Point T="0" X="239.0" Y="130.0"/>
<Point T="0" X="239.0" Y="130.0"/>
<Point T="0" X="239.0" Y="130.0"/>
<Point T="0" X="239.0" Y="130.0"/>
<Point T="0" X="239.0" Y="130.0"/>
<Point T="0" X="240.0" Y="130.0"/>
<Point T="0" X="240.0" Y="129.0"/>
<Point T="0" X="241.0" Y="129.0"/>
<Point T="0" X="243.0" Y="128.0"/>
<Point T="0" X="247.0" Y="126.0"/>
<Point T="0" X="253.0" Y="125.0"/>
<Point T="0" X="261.0" Y="125.0"/>
<Point T="0" X="268.0" Y="124.0"/>
<Point T="0" X="274.0" Y="124.0"/>
<Point T="0" X="278.0" Y="124.0"/>
<Point T="0" X="280.0" Y="123.0"/>
<Point T="0" X="281.0" Y="123.0"/>
<Point T="0" X="281.0" Y="123.0"/>
<Point T="0" X="282.0" Y="123.0"/>
<Point T="0" X="282.0" Y="122.0"/>
<Point T="0" X="284.0" Y="122.0"/>
<Point T="0" X="285.0" Y="121.0"/>
<Point T="0" X="288.0" Y="121.0"/>
<Point T="0" X="290.0" Y="120.0"/>
<Point T="0" X="292.0" Y="120.0"/>
<Point T="0" X="292.0" Y="120.0"/>
<Point T="0" X="293.0" Y="119.0"/>
<Point T="0" X="293.0" Y="119.0"/>
<Point T="0" X="293.0" Y="119.0"/>
<Point T="0" X="293.0" Y="119.0"/>
<Point T="0" X="293.0" Y="119.0"/>
<Point T="0" X="293.0" Y="119.0"/>
<Point T="0" X="293.0" Y="118.0"/>
<Point T="0" X="293.0" Y="118.0"/>
<Point T="0" X="292.0" Y="117.0"/>
<Point T="0" X="291.0" Y="116.0"/>
<Point T="0" X="289.0" Y="115.0"/>
<Point T="0" X="288.0" Y="114.0"/>
<Point T="0" X="286.0" Y="112.0"/>
<Point T="0" X="283.0" Y="109.0"/>
<Point T="0" X="279.0" Y="106.0"/>
<Point T="0" X="275.0" Y="101.0"/>
<Point T="0" X="271.0" Y="97.0"/>
<Point T="0" X="267.0" Y="93.0"/>
<Point T="0" X="263.0" Y="90.0"/>
<Point T="0" X="260.0" Y="87.0"/>
<Point T="0" X="257.0" Y="84.0"/>
<Point T="0" X="255.0" Y="81.0"/>
<Point T="0" X="254.0" Y="80.0"/>
<Point T="0" X="253.0" Y="79.0"/>
<Point T="0" X="253.0" Y="79.0"/>
<Point T="0" X="253.0" Y="78.0"/>
<Point T="0" X="253.0" Y="78.0"/>
<Point T="0" X="253.0" Y="78.0"/>
<Point T="0" X="253.0" Y="78.0"/>
<Point T="0" X="253.0" Y="78.0"/>
<Point T="0" X="253.0" Y="79.0"/>
</Gesture>
