<?xml version="1.0" encoding="UTF-8" standalone="no"?>
<Gesture AppName="Gestures" AppVer="3.5.0.0" Date="Monday, March 05, 2007" Millseconds="1268" Name="left_curly_braces10" NumPts="109" Number="10" Speed="medium" Subject="2" TimeOfDay="9:12:24 PM">
<Point T="0" X="284.0" Y="59.0"/>
<Point T="0" X="284.0" Y="59.0"/>
<Point T="0" X="284.0" Y="59.0"/>
<Point T="0" X="284.0" Y="59.0"/>
<Point T="0" X="283.0" Y="59.0"/>
<Point T="0" X="282.0" Y="59.0"/>
<Point T="0" X="281.0" Y="59.0"/>
<Point T="0" X="280.0" Y="60.0"/>
<Point T="0" X="279.0" Y="61.0"/>
<Point T="0" X="279.0" Y="62.0"/>
<Point T="0" X="278.0" Y="63.0"/>
<Point T="0" X="277.0" Y="64.0"/>
<Point T="0" X="277.0" Y="65.0"/>
<Point T="0" X="276.0" Y="66.0"/>
<Point T="0" X="276.0" Y="67.0"/>
<Point T="0" X="276.0" Y="67.0"/>
<Point T="0" X="276.0" Y="68.0"/>
<Point T="0" X="276.0" Y="68.0"/>
<Point T="0" X="276.0" Y="69.0"/>
<Point T="0" X="275.0" Y="69.0"/>
<Point T="0" X="275.0" Y="70.0"/>
<Point T="0" X="275.0" Y="70.0"/>
<Point T="0" X="275.0" Y="70.0"/>
<Point T="0" X="275.0" Y="70.0"/>
<Point T="0" X="275.0" Y="71.0"/>
<Point T="0" X="275.0" Y="71.0"/>
<Point T="0" X="275.0" Y="71.0"/>
<Point T="0" X="275.0" Y="71.0"/>
<Point T="0" X="275.0" Y="72.0"/>
<Point T="0" X="276.0" Y="72.0"/>
<Point T="0" X="276.0" Y="73.0"/>
<Point T="0" X="276.0" Y="74.0"/>
<Point T="0" X="276.0" Y="74.0"/>
<Point T="0" X="276.0" Y="75.0"/>
<Point T="0" X="276.0" Y="77.0"/>
<Point T="0" X="276.0" Y="78.0"/>
<Point T="0" X="276.0" Y="80.0"/>
<Point T="0" X="276.0" Y="81.0"/>
<Point T="0" X="276.0" Y="83.0"/>
<Point T="0" X="276.0" Y="85.0"/>
<Point T="0" X="276.0" Y="86.0"/>
<Point T="0" X="276.0" Y="88.0"/>
<Point T="0" X="276.0" Y="89.0"/>
<Point T="0" X="276.0" Y="91.0"/>
<Point T="0" X="275.0" Y="92.0"/>
<Point T="0" X="275.0" Y="93.0"/>
<Point T="0" X="274.0" Y="94.0"/>
<Point T="0" X="274.0" Y="94.0"/>
<Point T="0" X="273.0" Y="95.0"/>
<Point T="0" X="273.0" Y="96.0"/>
<Point T="0" X="272.0" Y="96.0"/>
<Point T="0" X="272.0" Y="97.0"/>
<Point T="0" X="271.0" Y="97.0"/>
<Point T="0" X="271.0" Y="97.0"/>
<Point T="0" X="270.0" Y="97.0"/>
<Point T="0" X="269.0" Y="98.0"/>
<Point T="0" X="269.0" Y="98.0"/>
<Point T="0" X="269.0" Y="98.0"/>
<Point T="0" X="268.0" Y="98.0"/>
<Point T="0" X="268.0" Y="98.0"/>
<Point T="0" X="268.0" Y="98.0"/>
<Point T="0" X="268.0" Y="98.0"/>
<Point T="0" X="268.0" Y="98.0"/>
<Point T="0" X="269.0" Y="98.0"/>
<Point T="0" X="270.0" Y="98.0"/>
<Point T="0" X="270.0" Y="98.0"/>
<Point T="0" X="271.0" Y="98.0"/>
<Point T="0" X="271.0" Y="98.0"/>
<Point T="0" X="272.0" Y="98.0"/>
<Point T="0" X="273.0" Y="98.0"/>
<Point T="0" X="273.0" Y="99.0"/>
<Point T="0" X="274.0" Y="100.0"/>
<Point T="0" X="274.0" Y="101.0"/>
<Point T="0" X="274.0" Y="103.0"/>
<Point T="0" X="274.0" Y="105.0"/>
<Point T="0" X="274.0" Y="108.0"/>
<Point T="0" X="274.0" Y="111.0"/>
<Point T="0" X="274.0" Y="114.0"/>
<Point T="0" X="275.0" Y="117.0"/>
<Point T="0" X="275.0" Y="121.0"/>
<Point T="0" X="275.0" Y="124.0"/>
<Point T="0" X="275.0" Y="126.0"/>
<Point T="0" X="275.0" Y="128.0"/>
<Point T="0" X="275.0" Y="129.0"/>
<Point T="0" X="276.0" Y="130.0"/>
<Point T="0" X="276.0" Y="131.0"/>
<Point T="0" X="276.0" Y="132.0"/>
<Point T="0" X="276.0" Y="133.0"/>
<Point T="0" X="277.0" Y="134.0"/>
<Point T="0" X="278.0" Y="134.0"/>
<Point T="0" X="279.0" Y="134.0"/>
<Point T="0" X="280.0" Y="134.0"/>
<Point T="0" X="282.0" Y="134.0"/>
<Point T="0" X="283.0" Y="134.0"/>
<Point T="0" X="284.0" Y="134.0"/>
<Point T="0" X="285.0" Y="134.0"/>
<Point T="0" X="286.0" Y="134.0"/>
<Point T="0" X="287.0" Y="133.0"/>
<Point T="0" X="288.0" Y="131.0"/>
<Point T="0" X="288.0" Y="130.0"/>
<Point T="0" X="289.0" Y="128.0"/>
<Point T="0" X="289.0" Y="127.0"/>
<Point T="0" X="289.0" Y="126.0"/>
<Point T="0" X="289.0" Y="126.0"/>
<Point T="0" X="289.0" Y="125.0"/>
<Point T="0" X="289.0" Y="125.0"/>
<Point T="0" X="289.0" Y="125.0"/>
<Point T="0" X="289.0" Y="125.0"/>
<Point T="0" X="287.0" Y="126.0"/>
</Gesture>
